bottem.py
bottem-1.dist-info/LICENSE
bottem-1.dist-info/METADATA
bottem-1.dist-info/WHEEL
bottem-1.dist-info/top_level.txt
bottem-1.dist-info/RECORD
